tempfifo/__init__.py
tempfifo/tempfifo.py
tempfifo-1.1.4.dist-info/LICENSE
tempfifo-1.1.4.dist-info/METADATA
tempfifo-1.1.4.dist-info/WHEEL
tempfifo-1.1.4.dist-info/top_level.txt
tempfifo-1.1.4.dist-info/RECORD
