Metadata-Version: 2.1
Name: tempfifo
Version: 1.1.4
Summary: This module creates temporary named pipes
Home-page: https://gitlab.com/aaylward/tempfifo
Author: Anthony Aylward
Author-email: aaylward@salk.edu
License: UNKNOWN
Platform: UNKNOWN
Classifier: Programming Language :: Python :: 3
Classifier: License :: OSI Approved :: MIT License
Classifier: Operating System :: OS Independent
License-File: LICENSE
